dragonlog/CallBook.py
dragonlog/CassiopeiaConsole.py
dragonlog/CassiopeiaConsole_ui.py
dragonlog/ColorPalettes.py
dragonlog/ContestDlg.py
dragonlog/ContestDlg_ui.py
dragonlog/ContestStatistics.py
dragonlog/ContestStatistics_ui.py
dragonlog/DragonLog.py
dragonlog/DragonLog_AppSelect.py
dragonlog/DragonLog_AppSelect_ui.py
dragonlog/DragonLog_MainWindow_ui.py
dragonlog/DragonLog_QSOForm.py
dragonlog/DragonLog_QSOForm_ui.py
dragonlog/DragonLog_Settings.py
dragonlog/DragonLog_Settings_ui.py
dragonlog/DragonLog_Statistics.py
dragonlog/DxSpots.py
dragonlog/DxSpots_ui.py
dragonlog/ListEdit.py
dragonlog/ListEdit_ui.py
dragonlog/LoTW.py
dragonlog/Logger.py
dragonlog/QSLQRReader.py
dragonlog/QSLQRReader_ui.py
dragonlog/RegEx.py
dragonlog/RigControl.py
dragonlog/SelectWidget.py
dragonlog/SelectWidget_ui.py
dragonlog/__init__.py
dragonlog/__main__.py
dragonlog/__version__.py
dragonlog/cty.py
dragonlog/distance.py
dragonlog/eQSL.py
dragonlog/local_callbook.py
dragonlog/contest/__init__.py
dragonlog/contest/__main__.py
dragonlog/contest/base.py
dragonlog/contest/contests_darc.py
dragonlog/contest/contests_darc_others.py
dragonlog/contest/contests_darc_rlp.py
dragonlog/contest/contests_others.py
dragonlog/contest/data/Logvorlage_V1_FM_K32.xlsx
dragonlog/data/AVAILABLE_CONTESTS.md
dragonlog/data/HAMCC_DE.md
dragonlog/data/HAMCC_EN.md
dragonlog/data/HELP_DE.md
dragonlog/data/HELP_EN.md
dragonlog/data/InterSlashedZero.sfd
dragonlog/data/InterSlashedZero.ttf
dragonlog/data/SHORTCUTS_DE.md
dragonlog/data/SHORTCUTS_EN.md
dragonlog/data/bands.json
dragonlog/data/cb_channels.json
dragonlog/data/color_map.json
dragonlog/data/modes.json
dragonlog/data/cty/HISTORY.TXT
dragonlog/data/cty/README.TXT
dragonlog/data/cty/copyright.txt
dragonlog/data/cty/cty.csv
dragonlog/data/i18n/DragonLog_de.qm
dragonlog/data/i18n/DragonLog_en.qm
dragonlog/data/i18n/DragonLog_templ.qm
dragonlog/data/i18n/ascii_replace_de.json
dragonlog/icons/Screenshot.png
dragonlog/icons/callbook_export.png
dragonlog-25.12.dist-info/licenses/LICENCE.txt
dragonlog-25.12.dist-info/METADATA
dragonlog-25.12.dist-info/WHEEL
dragonlog-25.12.dist-info/entry_points.txt
dragonlog-25.12.dist-info/top_level.txt
dragonlog-25.12.dist-info/RECORD
