Metadata-Version: 2.4
Name: DragonLog
Version: 25.12
Summary: Log QSO for Ham radio
Author-email: "Andreas Schawo, DF1ASC" <andreas@schawo.de>
Project-URL: Homepage, https://codeberg.org/dragoncode/DragonLog#readme
Project-URL: Bug Tracker, https://codeberg.org/dragoncode/DragonLog/issues
Classifier: Development Status :: 5 - Production/Stable
Classifier: Intended Audience :: End Users/Desktop
Classifier: Operating System :: OS Independent
Classifier: Programming Language :: Python :: 3 :: Only
Classifier: Programming Language :: Python :: 3.10
Classifier: Programming Language :: Python :: 3.11
Classifier: Programming Language :: Python :: 3.12
Classifier: Programming Language :: Python :: 3.13
Classifier: Topic :: Communications :: Ham Radio
Requires-Python: >=3.10
License-File: LICENCE.txt
Requires-Dist: PyQt6
Requires-Dist: maidenhead
Requires-Dist: PyADIF-File~=1.3
Requires-Dist: keyring
Requires-Dist: requests
Requires-Dist: xmltodict
Requires-Dist: HamCC~=1.0
Requires-Dist: numpy
Requires-Dist: matplotlib
Requires-Dist: packaging
Provides-Extra: xlformat
Requires-Dist: openpyxl; extra == "xlformat"
Provides-Extra: qslqrcode
Requires-Dist: opencv-python-headless; extra == "qslqrcode"
Requires-Dist: pyzbar; extra == "qslqrcode"
Dynamic: license-file
